[{"id":"4w3gZzOOA2jClS9Zjeyxhy","explicit":true,"artist_id":"6NyJIFHAePjHR1pFxwisqz","artist_name":"Kurupt","album_id":"14l1av80eEmYtlIGbHb0yR","feats":"C-Mob, GOTTI MOB","feats_ids":"4MHbbhIPVJM9rq9exwwpZJ, 59PYlXPSKqFNPUtOXHtwgs","name":"Mid-West (Intro)","duration_ms":107438,"track_number":1,"track_type":"track"},{"id":"4j5oCeDsnrRMCj6PGapu6Y","explicit":true,"artist_id":"6NyJIFHAePjHR1pFxwisqz","artist_name":"Kurupt","album_id":"14l1av80eEmYtlIGbHb0yR","feats":"C-Mob, GOTTI MOB","feats_ids":"4MHbbhIPVJM9rq9exwwpZJ, 59PYlXPSKqFNPUtOXHtwgs","name":"Want Smoke!","duration_ms":195724,"track_number":2,"track_type":"track"},{"id":"4Z8eTE9PfBk18EKUeaFTy0","explicit":true,"artist_id":"6NyJIFHAePjHR1pFxwisqz","artist_name":"Kurupt","album_id":"14l1av80eEmYtlIGbHb0yR","feats":"C-Mob, GOTTI MOB, Too $hort","feats_ids":"4MHbbhIPVJM9rq9exwwpZJ, 59PYlXPSKqFNPUtOXHtwgs, 4sb7rZNN93BSS6Gqgepo4v","name":"Dumb Shit (Delirious)","duration_ms":212107,"track_number":3,"track_type":"track"},{"id":"6eFSiRKQYlJp1WNnEdMoqC","explicit":true,"artist_id":"6NyJIFHAePjHR1pFxwisqz","artist_name":"Kurupt","album_id":"14l1av80eEmYtlIGbHb0yR","feats":"C-Mob, GOTTI MOB","feats_ids":"4MHbbhIPVJM9rq9exwwpZJ, 59PYlXPSKqFNPUtOXHtwgs","name":"I Ain't Even Know","duration_ms":194836,"track_number":4,"track_type":"track"},{"id":"5aiVeAN2BbC8RcI9FwgsPQ","explicit":true,"artist_id":"6NyJIFHAePjHR1pFxwisqz","artist_name":"Kurupt","album_id":"14l1av80eEmYtlIGbHb0yR","feats":"C-Mob, GOTTI MOB, Snoop Dogg","feats_ids":"4MHbbhIPVJM9rq9exwwpZJ, 59PYlXPSKqFNPUtOXHtwgs, 7hJcb9fa4alzcOq3EaNPoG","name":"Players Ball","duration_ms":266428,"track_number":5,"track_type":"track"},{"id":"277KA2qY1Y3zPPlADlI7Sh","explicit":true,"artist_id":"6NyJIFHAePjHR1pFxwisqz","artist_name":"Kurupt","album_id":"14l1av80eEmYtlIGbHb0yR","feats":"C-Mob, GOTTI MOB","feats_ids":"4MHbbhIPVJM9rq9exwwpZJ, 59PYlXPSKqFNPUtOXHtwgs","name":"Da Bizne$$","duration_ms":185142,"track_number":6,"track_type":"track"},{"id":"0r1QdPRP58kJFeD2vlWvah","explicit":true,"artist_id":"6NyJIFHAePjHR1pFxwisqz","artist_name":"Kurupt","album_id":"14l1av80eEmYtlIGbHb0yR","feats":"C-Mob, GOTTI MOB, Kendrick Lamar, Tech N9ne","feats_ids":"4MHbbhIPVJM9rq9exwwpZJ, 59PYlXPSKqFNPUtOXHtwgs, 2YZyLoL8N0Wb9xBt1NhZWg, 6UBA15slIuadJ8h2lPRPos","name":"Game Recognize Game (Interlude)","duration_ms":68603,"track_number":7,"track_type":"track"},{"id":"5uisxHyJtsNIb1disdtFiB","explicit":true,"artist_id":"6NyJIFHAePjHR1pFxwisqz","artist_name":"Kurupt","album_id":"14l1av80eEmYtlIGbHb0yR","feats":"C-Mob, GOTTI MOB, X-Raided","feats_ids":"4MHbbhIPVJM9rq9exwwpZJ, 59PYlXPSKqFNPUtOXHtwgs, 3ROTuxpbVooOYY7OanW7No","name":"Often","duration_ms":279272,"track_number":8,"track_type":"track"},{"id":"5KLJjD5NF4qCzsXpOVzuZm","explicit":true,"artist_id":"6NyJIFHAePjHR1pFxwisqz","artist_name":"Kurupt","album_id":"14l1av80eEmYtlIGbHb0yR","feats":"C-Mob, GOTTI MOB","feats_ids":"4MHbbhIPVJM9rq9exwwpZJ, 59PYlXPSKqFNPUtOXHtwgs","name":"Take Me Away","duration_ms":201771,"track_number":9,"track_type":"track"},{"id":"4TGrX7zPHpc1Ujq0qD39I3","explicit":true,"artist_id":"6NyJIFHAePjHR1pFxwisqz","artist_name":"Kurupt","album_id":"14l1av80eEmYtlIGbHb0yR","feats":"C-Mob, GOTTI MOB, MC Eiht","feats_ids":"4MHbbhIPVJM9rq9exwwpZJ, 59PYlXPSKqFNPUtOXHtwgs, 4XqfpACObRB5AsBcUYjL8X","name":"Medicine","duration_ms":284571,"track_number":10,"track_type":"track"},{"id":"5mn9n6UGx4oTTXKZogs6jg","explicit":true,"artist_id":"6NyJIFHAePjHR1pFxwisqz","artist_name":"Kurupt","album_id":"14l1av80eEmYtlIGbHb0yR","feats":"C-Mob, GOTTI MOB","feats_ids":"4MHbbhIPVJM9rq9exwwpZJ, 59PYlXPSKqFNPUtOXHtwgs","name":"Move Nice","duration_ms":257644,"track_number":11,"track_type":"track"},{"id":"4kRTPjEofdHPR6wGs3cjL1","explicit":true,"artist_id":"6NyJIFHAePjHR1pFxwisqz","artist_name":"Kurupt","album_id":"14l1av80eEmYtlIGbHb0yR","feats":"C-Mob, GOTTI MOB","feats_ids":"4MHbbhIPVJM9rq9exwwpZJ, 59PYlXPSKqFNPUtOXHtwgs","name":"Wanna Be A Ho","duration_ms":228462,"track_number":12,"track_type":"track"},{"id":"3rqIsulqa0b6Q5PZHRpaTa","explicit":true,"artist_id":"6NyJIFHAePjHR1pFxwisqz","artist_name":"Kurupt","album_id":"14l1av80eEmYtlIGbHb0yR","feats":"C-Mob, GOTTI MOB, KXNG Crooked, Spice 1","feats_ids":"4MHbbhIPVJM9rq9exwwpZJ, 59PYlXPSKqFNPUtOXHtwgs, 6fFfnKGVI6X3lkCr8Qw1g1, 4TqmaFJYM8SvuhrunxpmT3","name":"Everywhere (BONUS TRACK)","duration_ms":316116,"track_number":13,"track_type":"track"}]