[{"id":"0T3wULmGVmHtwQ3RdwXpxu","explicit":true,"artist_id":"4cUkGQyhLFqKHBtL58HYVp","artist_name":"Channel Tres","album_id":"1p2LdU7Q9Aq8OjO8sfnVMU","feats":"","feats_ids":"","name":"i can't go outside - intro","duration_ms":157305,"track_number":1,"track_type":"track"},{"id":"3c1RaJgNdwLHLPBYTVE1wb","explicit":true,"artist_id":"4cUkGQyhLFqKHBtL58HYVp","artist_name":"Channel Tres","album_id":"1p2LdU7Q9Aq8OjO8sfnVMU","feats":"","feats_ids":"","name":"2000 chevy malibu","duration_ms":162148,"track_number":2,"track_type":"track"},{"id":"3k6dcqiGHWhMNIPqWiWNX8","explicit":true,"artist_id":"4cUkGQyhLFqKHBtL58HYVp","artist_name":"Channel Tres","album_id":"1p2LdU7Q9Aq8OjO8sfnVMU","feats":"","feats_ids":"","name":"skate depot","duration_ms":186423,"track_number":3,"track_type":"track"},{"id":"6JxL32LcEK884H0LYmvtp6","explicit":true,"artist_id":"4cUkGQyhLFqKHBtL58HYVp","artist_name":"Channel Tres","album_id":"1p2LdU7Q9Aq8OjO8sfnVMU","feats":"","feats_ids":"","name":"broke down kid interlude","duration_ms":155456,"track_number":4,"track_type":"track"},{"id":"6UYbt0ZVXP5pnrhzk8z2d8","explicit":true,"artist_id":"4cUkGQyhLFqKHBtL58HYVp","artist_name":"Channel Tres","album_id":"1p2LdU7Q9Aq8OjO8sfnVMU","feats":"Tyler, The Creator","feats_ids":"4V8LLVI7PbaPR0K2TGSxFF","name":"fuego (feat. Tyler, The Creator)","duration_ms":248764,"track_number":5,"track_type":"track"},{"id":"2AvoxIbaR1vmZe6sCmigaF","explicit":false,"artist_id":"4cUkGQyhLFqKHBtL58HYVp","artist_name":"Channel Tres","album_id":"1p2LdU7Q9Aq8OjO8sfnVMU","feats":"Tinashe","feats_ids":"0NIIxcxNHmOoyBx03SfTCD","name":"take your time (feat. Tinashe)","duration_ms":191261,"track_number":6,"track_type":"track"},{"id":"12IP3NG2rCZPgTSxh0qAUc","explicit":true,"artist_id":"4cUkGQyhLFqKHBtL58HYVp","artist_name":"Channel Tres","album_id":"1p2LdU7Q9Aq8OjO8sfnVMU","feats":"","feats_ids":"","name":"unfinished business","duration_ms":186538,"track_number":7,"track_type":"track"}]