[{"id":"1ILB21dk7nGTDMLUvRy34X","explicit":false,"artist_id":"2oVrruuEI0Dr2I4NvLtQS0","artist_name":"Clara Luciani","album_id":"3EThsjrVO1Rzphdzxuh2xt","feats":"","feats_ids":"","name":"Nue","duration_ms":184066,"track_number":1,"track_type":"track"},{"id":"1YEiBBhJrLyKivGIvX1Dvc","explicit":false,"artist_id":"5MmVJVhhYKQ86izuGHzJYA","artist_name":"MIKA","album_id":"3EThsjrVO1Rzphdzxuh2xt","feats":"","feats_ids":"","name":"C’est la Vie","duration_ms":208469,"track_number":2,"track_type":"track"},{"id":"4tkqysN1xPXHTX6aLxJMXB","explicit":false,"artist_id":"7wjeXCtRND2ZdKfMJFu6JC","artist_name":"Louane","album_id":"3EThsjrVO1Rzphdzxuh2xt","feats":"","feats_ids":"","name":"Le bateau coule","duration_ms":199426,"track_number":3,"track_type":"track"},{"id":"5KhTD3nZ5gDMMB7PnLRmC5","explicit":false,"artist_id":"1AT7xbkG9hKbNlvGfZtA7S","artist_name":"The Doug","album_id":"3EThsjrVO1Rzphdzxuh2xt","feats":"","feats_ids":"","name":"Génération","duration_ms":172213,"track_number":4,"track_type":"track"},{"id":"6tm6L43IJC9bgJrAS5WXam","explicit":false,"artist_id":"3QVolfxko2UyCOtexhVTli","artist_name":"Angèle","album_id":"3EThsjrVO1Rzphdzxuh2xt","feats":"","feats_ids":"","name":"Le temps fera les choses","duration_ms":178466,"track_number":5,"track_type":"track"},{"id":"7H7GmGQifb1l2RCW11bmDJ","explicit":false,"artist_id":"0fCV53y12NSwAgq3WnwO99","artist_name":"Saan","album_id":"3EThsjrVO1Rzphdzxuh2xt","feats":"","feats_ids":"","name":"Jouet","duration_ms":158413,"track_number":6,"track_type":"track"},{"id":"1uYIlpLQwcnOSvseLTTXOr","explicit":false,"artist_id":"4IS4EyXNmiI2w5SRCjMtEF","artist_name":"Kendji Girac","album_id":"3EThsjrVO1Rzphdzxuh2xt","feats":"","feats_ids":"","name":"Eva","duration_ms":220359,"track_number":7,"track_type":"track"},{"id":"57ejcU9xoFMqZWwDENKvwU","explicit":false,"artist_id":"5Ha8JdCWeJ8vdqEhzgiSU5","artist_name":"Maëlle","album_id":"3EThsjrVO1Rzphdzxuh2xt","feats":"","feats_ids":"","name":"La flemme","duration_ms":196520,"track_number":8,"track_type":"track"},{"id":"5rUkiUYhCVpq9MBXg8RSbR","explicit":false,"artist_id":"61CPKXT0bcKj8MKTNTMOXa","artist_name":"Juliette Armanet","album_id":"3EThsjrVO1Rzphdzxuh2xt","feats":"","feats_ids":"","name":"Qu'importe","duration_ms":226866,"track_number":9,"track_type":"track"},{"id":"6JuQBq9TOIIe9um29pJDTs","explicit":false,"artist_id":"0NkmvuSD5Pm8zucjwIpChS","artist_name":"La Zarra","album_id":"3EThsjrVO1Rzphdzxuh2xt","feats":"","feats_ids":"","name":"Tu t’en iras","duration_ms":205840,"track_number":10,"track_type":"track"},{"id":"7izQ4at1ma3WFJ5PHvdw3T","explicit":false,"artist_id":"4hCY20IkGa63aUoV82yMBE","artist_name":"Victorien","album_id":"3EThsjrVO1Rzphdzxuh2xt","feats":"","feats_ids":"","name":"Embrasse-moi","duration_ms":166173,"track_number":11,"track_type":"track"},{"id":"6CX3M5t81ynGKnFXAkMfZy","explicit":false,"artist_id":"3mNXGOPYzxYiGxttEvJ9hx","artist_name":"Hervé","album_id":"3EThsjrVO1Rzphdzxuh2xt","feats":"","feats_ids":"","name":"Tout ira mieux demain","duration_ms":210466,"track_number":12,"track_type":"track"},{"id":"5mtdcH7eJBCQRhsOg90BhV","explicit":false,"artist_id":"3L4wiBOSDLkJ18OISXZDA8","artist_name":"Barbara Pravi","album_id":"3EThsjrVO1Rzphdzxuh2xt","feats":"Emel","feats_ids":"06MtOym27ALcfdtVOsRcaA","name":"Lève-toi","duration_ms":214296,"track_number":13,"track_type":"track"},{"id":"5k4pwy7Od0ZTRa2VeW7USr","explicit":false,"artist_id":"1AT7xbkG9hKbNlvGfZtA7S","artist_name":"The Doug","album_id":"3EThsjrVO1Rzphdzxuh2xt","feats":"","feats_ids":"","name":"réparer","duration_ms":178800,"track_number":14,"track_type":"track"},{"id":"4ZI4ySZeUbbqF1xcMaJ1SC","explicit":false,"artist_id":"3BAyGVtoPcmQbeb58hlIZs","artist_name":"CHARLES","album_id":"3EThsjrVO1Rzphdzxuh2xt","feats":"","feats_ids":"","name":"le marbre","duration_ms":142062,"track_number":15,"track_type":"track"},{"id":"2Th8kPTMYHGGLeYgbSIuP0","explicit":false,"artist_id":"3mNXGOPYzxYiGxttEvJ9hx","artist_name":"Hervé","album_id":"3EThsjrVO1Rzphdzxuh2xt","feats":"","feats_ids":"","name":"Sémaphore","duration_ms":164666,"track_number":16,"track_type":"track"},{"id":"2FGwbj9QzUtTg9lgKiydZB","explicit":false,"artist_id":"7wjeXCtRND2ZdKfMJFu6JC","artist_name":"Louane","album_id":"3EThsjrVO1Rzphdzxuh2xt","feats":"","feats_ids":"","name":"A quoi tu penses vraiment","duration_ms":175483,"track_number":17,"track_type":"track"},{"id":"1BVrAyp0g60wxM34Id8bsn","explicit":false,"artist_id":"7rFugkk9ZvVB1zXHg8h0rj","artist_name":"Eddy de Pretto","album_id":"3EThsjrVO1Rzphdzxuh2xt","feats":"","feats_ids":"","name":"urgences 911","duration_ms":177880,"track_number":18,"track_type":"track"},{"id":"0O4Gey7s0bSVn5KoZzotza","explicit":false,"artist_id":"5Ha8JdCWeJ8vdqEhzgiSU5","artist_name":"Maëlle","album_id":"3EThsjrVO1Rzphdzxuh2xt","feats":"","feats_ids":"","name":"Ouvrir les yeux","duration_ms":203359,"track_number":19,"track_type":"track"},{"id":"6qEtWOh5NNfORXhi7NxUHg","explicit":false,"artist_id":"3mNXGOPYzxYiGxttEvJ9hx","artist_name":"Hervé","album_id":"3EThsjrVO1Rzphdzxuh2xt","feats":"","feats_ids":"","name":"Comme tout le monde","duration_ms":159160,"track_number":20,"track_type":"track"},{"id":"17bZCQt6yHD1qkkz207OeF","explicit":false,"artist_id":"5KbznS5SUZOb7skpdIO9J6","artist_name":"Elia","album_id":"3EThsjrVO1Rzphdzxuh2xt","feats":"","feats_ids":"","name":"Délit de mélancolie","duration_ms":168653,"track_number":21,"track_type":"track"},{"id":"1gCisxvOlsQDDkmx1dKvbU","explicit":false,"artist_id":"4IS4EyXNmiI2w5SRCjMtEF","artist_name":"Kendji Girac","album_id":"3EThsjrVO1Rzphdzxuh2xt","feats":"","feats_ids":"","name":"Conquistador","duration_ms":222213,"track_number":22,"track_type":"track"},{"id":"0jP44jEfJo5pP2680p0FUR","explicit":false,"artist_id":"3QVolfxko2UyCOtexhVTli","artist_name":"Angèle","album_id":"3EThsjrVO1Rzphdzxuh2xt","feats":"","feats_ids":"","name":"Plus de sens","duration_ms":209605,"track_number":23,"track_type":"track"},{"id":"0R8hvSHQMXUJgz14uVsoAB","explicit":false,"artist_id":"7wjeXCtRND2ZdKfMJFu6JC","artist_name":"Louane","album_id":"3EThsjrVO1Rzphdzxuh2xt","feats":"","feats_ids":"","name":"Jour 1 - Birthday Party Version","duration_ms":179410,"track_number":24,"track_type":"track"},{"id":"7A7grzK38rgSDl38CGbIvJ","explicit":false,"artist_id":"5Nq9MbzweBc5oL4WzsECx4","artist_name":"Calogero","album_id":"3EThsjrVO1Rzphdzxuh2xt","feats":"","feats_ids":"","name":"Je joue de la musique","duration_ms":240918,"track_number":25,"track_type":"track"},{"id":"5K9gug3c7yD9jA2pxNOQmN","explicit":false,"artist_id":"6euPnGzBlDysAC5ecVguNZ","artist_name":"M. Pokora","album_id":"3EThsjrVO1Rzphdzxuh2xt","feats":"Sweety","feats_ids":"2rjn0MFHWBb46JOGo1yasB","name":"Elle me contrôle","duration_ms":226400,"track_number":26,"track_type":"track"},{"id":"0GLQgKPm1rrm08LdDdAWrd","explicit":false,"artist_id":"61CPKXT0bcKj8MKTNTMOXa","artist_name":"Juliette Armanet","album_id":"3EThsjrVO1Rzphdzxuh2xt","feats":"","feats_ids":"","name":"Le Dernier Jour du Disco - Remix","duration_ms":151706,"track_number":27,"track_type":"track"},{"id":"2yUSW7bsAxf2cw1z2MGZOB","explicit":false,"artist_id":"5j4HeCoUlzhfWtjAfM1acR","artist_name":"Stromae","album_id":"3EThsjrVO1Rzphdzxuh2xt","feats":"","feats_ids":"","name":"Ta fête","duration_ms":175426,"track_number":28,"track_type":"track"},{"id":"2LSOuCndJNgg78fk90sCe5","explicit":false,"artist_id":"4IS4EyXNmiI2w5SRCjMtEF","artist_name":"Kendji Girac","album_id":"3EThsjrVO1Rzphdzxuh2xt","feats":"","feats_ids":"","name":"Desperado","duration_ms":198973,"track_number":29,"track_type":"track"},{"id":"4YHVdMF33hF4xE0QL9j60z","explicit":false,"artist_id":"7wjeXCtRND2ZdKfMJFu6JC","artist_name":"Louane","album_id":"3EThsjrVO1Rzphdzxuh2xt","feats":"","feats_ids":"","name":"Jour de pluie","duration_ms":179506,"track_number":30,"track_type":"track"}]