[{"id":"4UhrsnNCaCKEBbYGFs20fT","explicit":false,"artist_id":"3zaxUd86U92CdZkNa6NUo9","artist_name":"Ark Patrol","album_id":"3nUlSVSKT3hXDHpJd59crs","feats":"FiFi Zhang","feats_ids":"059v3EegVz2AonSh0Ro75Y","name":"Tomorrow Can Wait","duration_ms":160667,"track_number":1,"track_type":"track"},{"id":"6moZO608WNPGMBSE3tZoVr","explicit":false,"artist_id":"3zaxUd86U92CdZkNa6NUo9","artist_name":"Ark Patrol","album_id":"3nUlSVSKT3hXDHpJd59crs","feats":"Veronika Redd","feats_ids":"6kuFWCCvd7bWB1PV0tJMN2","name":"Oui","duration_ms":393100,"track_number":2,"track_type":"track"}]