[{"id":"1H42E8srHxjM9JRdt98ira","explicit":false,"artist_id":"0xRXCcSX89eobfrshSVdyu","artist_name":"MEDUZA","album_id":"3sEKHdAwlCOwRymaRriRp6","feats":"Becky Hill, Goodboys","feats_ids":"4EPJlUEBy49EX1wuFOvtjK, 2nm38smINjms1LtczR0Cei","name":"Lose Control","duration_ms":168387,"track_number":1,"track_type":"track"},{"id":"4t5JQAMUH55bTRE1oHQy0f","explicit":false,"artist_id":"7ACEUD7UsmmXrnj4OLt8f9","artist_name":"twocolors","album_id":"3sEKHdAwlCOwRymaRriRp6","feats":"","feats_ids":"","name":"Lovefool","duration_ms":190733,"track_number":2,"track_type":"track"},{"id":"4uP3DLFKCdwujKXEJ3TEH2","explicit":false,"artist_id":"3bBb1wCpTPxl3KRfb2UbJb","artist_name":"Mike Vallas","album_id":"3sEKHdAwlCOwRymaRriRp6","feats":"","feats_ids":"","name":"The Other Side","duration_ms":169986,"track_number":3,"track_type":"track"},{"id":"3SUeOoF7Q0EpVgi9r1qL5f","explicit":false,"artist_id":"53XhwfbYqKCa1cC15pYq2q","artist_name":"Imagine Dragons","album_id":"3sEKHdAwlCOwRymaRriRp6","feats":"","feats_ids":"","name":"Natural","duration_ms":189466,"track_number":4,"track_type":"track"},{"id":"2GL2wooU2lmipDlTugV6TC","explicit":false,"artist_id":"1w67D3PakcxjYGt6xPnnke","artist_name":"Darius & Finlay","album_id":"3sEKHdAwlCOwRymaRriRp6","feats":"","feats_ids":"","name":"Clothes Off (Nanana)","duration_ms":226629,"track_number":5,"track_type":"track"},{"id":"6zlfDLkDwbK3MPxO3zGMkU","explicit":true,"artist_id":"0u6GtibW46tFX7koQ6uNJZ","artist_name":"Topic","album_id":"3sEKHdAwlCOwRymaRriRp6","feats":"A7S, HUGEL","feats_ids":"5Wg2b4Mp42gicxEeDNawf7, 5PlfkPxwCpRRWQJBxCa0By","name":"Breaking Me - HUGEL Remix","duration_ms":171904,"track_number":6,"track_type":"track"},{"id":"2OAbWBEllhLMliqzdVn1C7","explicit":false,"artist_id":"7AjItKsRnEYRSiBt2OxK1y","artist_name":"FVLCRVM","album_id":"3sEKHdAwlCOwRymaRriRp6","feats":"","feats_ids":"","name":"Hate List","duration_ms":209127,"track_number":7,"track_type":"track"},{"id":"2opAroGSWUnyGcts898C12","explicit":false,"artist_id":"1lmU3giNF3CSbkVSQmLpHQ","artist_name":"Surf Mesa","album_id":"3sEKHdAwlCOwRymaRriRp6","feats":"Topic, Emilee","feats_ids":"0u6GtibW46tFX7koQ6uNJZ, 4ArPQ1Opcksbbf3CPwEjWE","name":"ily (i love you baby) - Topic Remix","duration_ms":156960,"track_number":8,"track_type":"track"},{"id":"7hkUXWjBOtH1aooFyfsUPD","explicit":false,"artist_id":"44rZECdV2X0ON9VAc7iOFh","artist_name":"Marija","album_id":"3sEKHdAwlCOwRymaRriRp6","feats":"Indigo","feats_ids":"0umoAerEf5lGiB9OJvMp4W","name":"Louder Than A Drum - Indigo Remix","duration_ms":247493,"track_number":9,"track_type":"track"},{"id":"5pZtU8w8uG767Wqx7Zaq4d","explicit":false,"artist_id":"0xRXCcSX89eobfrshSVdyu","artist_name":"MEDUZA","album_id":"3sEKHdAwlCOwRymaRriRp6","feats":"Goodboys","feats_ids":"2nm38smINjms1LtczR0Cei","name":"Piece Of Your Heart","duration_ms":152913,"track_number":10,"track_type":"track"},{"id":"45b21BBQRO7oCtQ4z8iyoX","explicit":false,"artist_id":"4bL2B6hmLlMWnUEZnorEtG","artist_name":"Felix Jaehn","album_id":"3sEKHdAwlCOwRymaRriRp6","feats":"Jasmine Thompson","feats_ids":"2TL8gYTNgD6nXkyuUdDrMg","name":"Ain't Nobody (Loves Me Better)","duration_ms":240840,"track_number":11,"track_type":"track"},{"id":"7Ge0y6WFmxwh98dgj7Hocm","explicit":false,"artist_id":"11IUClvxg6PJtKQF2tRAOm","artist_name":"Felice & Pap","album_id":"3sEKHdAwlCOwRymaRriRp6","feats":"Bia","feats_ids":"1LjiV1UiEaF3DSHCAk11sF","name":"Electric Love - Extended Mix","duration_ms":360473,"track_number":12,"track_type":"track"},{"id":"3uLRPZPbvZQGjJYEBgd4KR","explicit":false,"artist_id":"5j4HeCoUlzhfWtjAfM1acR","artist_name":"Stromae","album_id":"3sEKHdAwlCOwRymaRriRp6","feats":"","feats_ids":"","name":"Alors on danse - Radio Edit","duration_ms":208146,"track_number":13,"track_type":"track"},{"id":"3KErNDdBbHUdMqlj4pUydZ","explicit":false,"artist_id":"44rZECdV2X0ON9VAc7iOFh","artist_name":"Marija","album_id":"3sEKHdAwlCOwRymaRriRp6","feats":"","feats_ids":"","name":"Dance Like Nobody's Watching","duration_ms":195110,"track_number":14,"track_type":"track"},{"id":"6FRkdVyc2XzW3DchGtWuc0","explicit":false,"artist_id":"4uRYpUQZrNrY5t8tAv3XrD","artist_name":"NERO","album_id":"3sEKHdAwlCOwRymaRriRp6","feats":"","feats_ids":"","name":"Satisfy","duration_ms":284516,"track_number":15,"track_type":"track"},{"id":"5BsLJGWabEyzpt4Yu1GHDM","explicit":false,"artist_id":"3PUzVXdNnsJGPDTIU7xvqu","artist_name":"Livin' Joy","album_id":"3sEKHdAwlCOwRymaRriRp6","feats":"","feats_ids":"","name":"Dreamer - Janice Robinson Vocal","duration_ms":223535,"track_number":16,"track_type":"track"},{"id":"01G7huSzvrnNm4UUV01oWb","explicit":false,"artist_id":"1vCWHaC5f2uS3yhpwWbIA6","artist_name":"Avicii","album_id":"3sEKHdAwlCOwRymaRriRp6","feats":"","feats_ids":"","name":"Levels - Original Version","duration_ms":338866,"track_number":17,"track_type":"track"},{"id":"2bbcQwRyFnFULSdJTeQoZN","explicit":false,"artist_id":"4YLQaW1UU3mrVetC8gNkg5","artist_name":"3LAU","album_id":"3sEKHdAwlCOwRymaRriRp6","feats":"Bright Lights","feats_ids":"2AoeqcUs8DySgZRJ9yV4Ou","name":"How You Love Me","duration_ms":210468,"track_number":18,"track_type":"track"},{"id":"47tfLpQ0EYprTOj3XYmZS5","explicit":true,"artist_id":"2o5jDhtHVPhrJdv3cEQ99Z","artist_name":"Tiësto","album_id":"3sEKHdAwlCOwRymaRriRp6","feats":"Sevenn, Gucci Mane","feats_ids":"7bNqXqIrIfwJnipx7oGeU4, 13y7CgLHjMVRMDqxdx0Xdo","name":"BOOM","duration_ms":179512,"track_number":19,"track_type":"track"},{"id":"1CzA7w8v68fkI1o2EjhpzU","explicit":false,"artist_id":"2VAnyOxzJuSAj7XIuEOT38","artist_name":"AlunaGeorge","album_id":"3sEKHdAwlCOwRymaRriRp6","feats":"Tchami","feats_ids":"1KpCi9BOfviCVhmpI4G2sY","name":"You Know You Like It - Tchami Remix","duration_ms":304333,"track_number":20,"track_type":"track"},{"id":"7k6yymA1PKI2zC2nQmzdUc","explicit":false,"artist_id":"6nS5roXSAGhTGr34W6n7Et","artist_name":"Disclosure","album_id":"3sEKHdAwlCOwRymaRriRp6","feats":"Eliza Doolittle, Flume","feats_ids":"14L5rpGTLVUz1pD8fUeJB1, 6nxWCVXbOlEVRexSbLsTer","name":"You & Me - Flume Remix","duration_ms":282812,"track_number":21,"track_type":"track"},{"id":"5vzN8lOhV8ZECQmD28tX9Z","explicit":true,"artist_id":"1yxSLGMDHlW21z4YXirZDS","artist_name":"Black Eyed Peas","album_id":"3sEKHdAwlCOwRymaRriRp6","feats":"","feats_ids":"","name":"Pump It","duration_ms":213613,"track_number":22,"track_type":"track"},{"id":"4s74GN9nZwmHHr7MvWuPIH","explicit":false,"artist_id":"6NbFlCK3uim4vJAtotD4Jd","artist_name":"Bunny Lake","album_id":"3sEKHdAwlCOwRymaRriRp6","feats":"","feats_ids":"","name":"Army Of Lovers - Radio Edit","duration_ms":219320,"track_number":23,"track_type":"track"},{"id":"2H8Ei0HqnXRfkVx6ek1PCc","explicit":false,"artist_id":"4EPJlUEBy49EX1wuFOvtjK","artist_name":"Becky Hill","album_id":"3sEKHdAwlCOwRymaRriRp6","feats":"WEISS","feats_ids":"0FBRY66KVaAiddGVefikLB","name":"I Could Get Used To This","duration_ms":193856,"track_number":24,"track_type":"track"},{"id":"58IaCSlpHdrwN9ZDKeOyiT","explicit":false,"artist_id":"2s7Oijd4mFGgEkhYJtf3sJ","artist_name":"Shane Codd","album_id":"3sEKHdAwlCOwRymaRriRp6","feats":"","feats_ids":"","name":"Get Out My Head","duration_ms":204933,"track_number":25,"track_type":"track"},{"id":"19XCaCSJs39ECuBKxlu7z0","explicit":false,"artist_id":"0X2BH1fck6amBIoJhDVmmJ","artist_name":"Ellie Goulding","album_id":"3sEKHdAwlCOwRymaRriRp6","feats":"","feats_ids":"","name":"Burn","duration_ms":231211,"track_number":26,"track_type":"track"},{"id":"6ogYgseK4eF65eszPoIzFm","explicit":false,"artist_id":"01vtTqN0YZQWngP19j3y71","artist_name":"Natália Kelly","album_id":"3sEKHdAwlCOwRymaRriRp6","feats":"","feats_ids":"","name":"Shine - Redio Ramix","duration_ms":238146,"track_number":27,"track_type":"track"},{"id":"6C5QxEgTwP2UE0xgObBTLB","explicit":false,"artist_id":"5KKpBU5eC2tJDzf0wmlRp2","artist_name":"RAYE","album_id":"3sEKHdAwlCOwRymaRriRp6","feats":"Rudimental","feats_ids":"4WN5naL3ofxrVBgFpguzKo","name":"Regardless","duration_ms":198506,"track_number":28,"track_type":"track"},{"id":"38fqmbZitkOSw43rHkMbXL","explicit":false,"artist_id":"1w67D3PakcxjYGt6xPnnke","artist_name":"Darius & Finlay","album_id":"3sEKHdAwlCOwRymaRriRp6","feats":"Maor Miller","feats_ids":"0ewFcI4uSjCul2FIERjQeF","name":"Not For Sale","duration_ms":207004,"track_number":29,"track_type":"track"},{"id":"6jUjCQQQFgu1lRsEs6NLVp","explicit":false,"artist_id":"01e2lCvLZ4fLUIRy68nptH","artist_name":"Wankelmut","album_id":"3sEKHdAwlCOwRymaRriRp6","feats":"SVEA","feats_ids":"4XtfY4CBieEfqF3CSiPrRx","name":"Give & Take","duration_ms":181000,"track_number":30,"track_type":"track"},{"id":"4tymCqlkAjT5CwwpWgH0Mk","explicit":false,"artist_id":"4Euia7UzdRshy1DJOSMTcs","artist_name":"220 KID","album_id":"3sEKHdAwlCOwRymaRriRp6","feats":"JC Stewart","feats_ids":"2TAqN8fwfaKauvviN4pOsv","name":"Too Many Nights","duration_ms":188636,"track_number":31,"track_type":"track"},{"id":"1HjHxvQoCdEUynL4GcA7T5","explicit":false,"artist_id":"4bL2B6hmLlMWnUEZnorEtG","artist_name":"Felix Jaehn","album_id":"3sEKHdAwlCOwRymaRriRp6","feats":"VIZE, Miss Li","feats_ids":"09agIJMxCD2k87ys9Al0f0, 04HqRx07Bv9gh7rsrMTqs7","name":"Close Your Eyes","duration_ms":159962,"track_number":32,"track_type":"track"},{"id":"2YTfYHcNn0NYjBzjGyBxzF","explicit":false,"artist_id":"33uhwUheWoyh63ggR3eZaL","artist_name":"Patrick Metzker","album_id":"3sEKHdAwlCOwRymaRriRp6","feats":"Baby Brown","feats_ids":"1I5rcDDRdsgBYmvEujrzi2","name":"Stars In The Sky - Original Mix","duration_ms":318749,"track_number":33,"track_type":"track"},{"id":"3jrc6TCGJNwPoJD7coev4N","explicit":false,"artist_id":"5jAMCwdNHWr7JThxtMuEyy","artist_name":"NOTD","album_id":"3sEKHdAwlCOwRymaRriRp6","feats":"Catello","feats_ids":"4cpqUkL78IoYnEvYj440WE","name":"Nobody","duration_ms":143952,"track_number":34,"track_type":"track"},{"id":"3IbbaHsjQ69UhFR8JPWBzx","explicit":false,"artist_id":"4EPJlUEBy49EX1wuFOvtjK","artist_name":"Becky Hill","album_id":"3sEKHdAwlCOwRymaRriRp6","feats":"","feats_ids":"","name":"Space","duration_ms":198291,"track_number":35,"track_type":"track"},{"id":"6WAhJdMqftin1TWb00KfdG","explicit":false,"artist_id":"7LiVklVR1325BIOqD9kykr","artist_name":"CLMD","album_id":"3sEKHdAwlCOwRymaRriRp6","feats":"Tungevaag","feats_ids":"49CE2ffZ6Z3zeYSDauSKck","name":"DANCE","duration_ms":174448,"track_number":36,"track_type":"track"},{"id":"1X1R0b0T3c76MIhwqJrt4g","explicit":false,"artist_id":"1moxjboGR7GNWYIMWsRjgG","artist_name":"Florence + The Machine","album_id":"3sEKHdAwlCOwRymaRriRp6","feats":"Calvin Harris","feats_ids":"7CajNmpbOovFoOoasH2HaY","name":"Spectrum (Say My Name) - Calvin Harris Remix","duration_ms":218190,"track_number":37,"track_type":"track"},{"id":"0MiOf2Vg9SEnoWwKWmKzWj","explicit":false,"artist_id":"4Q6nIcaBED8qUel8bBx6Cr","artist_name":"Jax Jones","album_id":"3sEKHdAwlCOwRymaRriRp6","feats":"Ina Wroldsen","feats_ids":"7hssUdpvtY5oiARaUDgFZ3","name":"Breathe","duration_ms":208106,"track_number":38,"track_type":"track"},{"id":"2IKdgZZswrDRlkNwz1Q5Bx","explicit":false,"artist_id":"7AjItKsRnEYRSiBt2OxK1y","artist_name":"FVLCRVM","album_id":"3sEKHdAwlCOwRymaRriRp6","feats":"","feats_ids":"","name":"Stray Dogs","duration_ms":203389,"track_number":39,"track_type":"track"},{"id":"2zfxeSafP5ANsnHsiZwzFp","explicit":false,"artist_id":"4UXqAaa6dQYAk18Lv7PEgX","artist_name":"Fall Out Boy","album_id":"3sEKHdAwlCOwRymaRriRp6","feats":"","feats_ids":"","name":"Centuries","duration_ms":228760,"track_number":40,"track_type":"track"},{"id":"2dx3YV0AhsygULQ2ojYVq0","explicit":false,"artist_id":"4AVFqumd2ogHFlRbKIjp1t","artist_name":"Alesso","album_id":"3sEKHdAwlCOwRymaRriRp6","feats":"Matthew Koma","feats_ids":"1mU61l2mcjEFraXZLpvVMo","name":"Years - Radio Edit","duration_ms":196346,"track_number":41,"track_type":"track"},{"id":"5ZhtjvGTnU17QI7JUUiHj2","explicit":false,"artist_id":"4NHQUGzhtTLFvgF5SZesLK","artist_name":"Tove Lo","album_id":"3sEKHdAwlCOwRymaRriRp6","feats":"The Chainsmokers","feats_ids":"69GGBxA162lTqCwzJG5jLp","name":"Habits (Stay High) - The Chainsmokers Extended Mix","duration_ms":294253,"track_number":42,"track_type":"track"},{"id":"1iE1G5s0MnhEo4t2GKrjLf","explicit":false,"artist_id":"09agIJMxCD2k87ys9Al0f0","artist_name":"VIZE","album_id":"3sEKHdAwlCOwRymaRriRp6","feats":"Felix Jaehn","feats_ids":"4bL2B6hmLlMWnUEZnorEtG","name":"Thank You [Not So Bad]","duration_ms":197963,"track_number":43,"track_type":"track"},{"id":"3WKQbWm5Ocz3pK4AMT7Fh9","explicit":false,"artist_id":"3yCRvilOBzRkyxOsOi4tsR","artist_name":"Viki Gabor","album_id":"3sEKHdAwlCOwRymaRriRp6","feats":"","feats_ids":"","name":"Not Gonna Get It","duration_ms":196474,"track_number":44,"track_type":"track"},{"id":"0UnSZYPNOHswsJQ18grEaM","explicit":false,"artist_id":"04gDigrS5kc9YWfZHwBETP","artist_name":"Maroon 5","album_id":"3sEKHdAwlCOwRymaRriRp6","feats":"Dillon Francis","feats_ids":"5R3Hr2cnCCjt220Jmt2xLf","name":"Memories - Dillon Francis Remix","duration_ms":162600,"track_number":45,"track_type":"track"}]