[{"id":"44KJlHUAxOUIgPSz04ZZ7T","explicit":false,"artist_id":"4d53BMrRlQkrQMz5d59f2O","artist_name":"Mayer Hawthorne","album_id":"4FF4II3GGoTuYRW3zenamA","feats":"","feats_ids":"","name":"Problematization","duration_ms":15066,"track_number":1,"track_type":"track"},{"id":"6cuQsekkJ92W3bXwObcUth","explicit":false,"artist_id":"4d53BMrRlQkrQMz5d59f2O","artist_name":"Mayer Hawthorne","album_id":"4FF4II3GGoTuYRW3zenamA","feats":"","feats_ids":"","name":"Back Seat Lover","duration_ms":231826,"track_number":2,"track_type":"track"},{"id":"58DBvHdJo1jEebHs9RHseA","explicit":false,"artist_id":"4d53BMrRlQkrQMz5d59f2O","artist_name":"Mayer Hawthorne","album_id":"4FF4II3GGoTuYRW3zenamA","feats":"","feats_ids":"","name":"The Innocent","duration_ms":202600,"track_number":3,"track_type":"track"},{"id":"58POte9bAmPFKLu13CJN1i","explicit":true,"artist_id":"4d53BMrRlQkrQMz5d59f2O","artist_name":"Mayer Hawthorne","album_id":"4FF4II3GGoTuYRW3zenamA","feats":"","feats_ids":"","name":"Allie Jones","duration_ms":244306,"track_number":4,"track_type":"track"},{"id":"5gkGnVQ1XAW0Ee2aZSAGkC","explicit":false,"artist_id":"4d53BMrRlQkrQMz5d59f2O","artist_name":"Mayer Hawthorne","album_id":"4FF4II3GGoTuYRW3zenamA","feats":"","feats_ids":"","name":"The Only One","duration_ms":200173,"track_number":5,"track_type":"track"},{"id":"5sohdX5mUJ4tQRwZfBMQnV","explicit":false,"artist_id":"4d53BMrRlQkrQMz5d59f2O","artist_name":"Mayer Hawthorne","album_id":"4FF4II3GGoTuYRW3zenamA","feats":"","feats_ids":"","name":"Wine Glass Woman","duration_ms":227906,"track_number":6,"track_type":"track"},{"id":"1oYzLN8ohivezf3sVQkg6K","explicit":false,"artist_id":"4d53BMrRlQkrQMz5d59f2O","artist_name":"Mayer Hawthorne","album_id":"4FF4II3GGoTuYRW3zenamA","feats":"","feats_ids":"","name":"Her Favorite Song","duration_ms":209293,"track_number":7,"track_type":"track"},{"id":"2wxbK6AqcjRiXRtlCCbr0s","explicit":false,"artist_id":"4d53BMrRlQkrQMz5d59f2O","artist_name":"Mayer Hawthorne","album_id":"4FF4II3GGoTuYRW3zenamA","feats":"","feats_ids":"","name":"Ay Bass Player","duration_ms":14120,"track_number":8,"track_type":"track"},{"id":"4QzFf6MGqsRz0WlH8E9qWv","explicit":true,"artist_id":"4d53BMrRlQkrQMz5d59f2O","artist_name":"Mayer Hawthorne","album_id":"4FF4II3GGoTuYRW3zenamA","feats":"Kendrick Lamar","feats_ids":"2YZyLoL8N0Wb9xBt1NhZWg","name":"Crime","duration_ms":280400,"track_number":9,"track_type":"track"},{"id":"5ZK9yfnwZduceyHM8tBwiU","explicit":false,"artist_id":"4d53BMrRlQkrQMz5d59f2O","artist_name":"Mayer Hawthorne","album_id":"4FF4II3GGoTuYRW3zenamA","feats":"","feats_ids":"","name":"Reach Out Richard","duration_ms":248240,"track_number":10,"track_type":"track"},{"id":"5U9fRIdPLqvia8MLPHhQp1","explicit":false,"artist_id":"4d53BMrRlQkrQMz5d59f2O","artist_name":"Mayer Hawthorne","album_id":"4FF4II3GGoTuYRW3zenamA","feats":"","feats_ids":"","name":"Corsican Rosé","duration_ms":248733,"track_number":11,"track_type":"track"},{"id":"6hkfC3gIN1veTOgNgGelpw","explicit":false,"artist_id":"4d53BMrRlQkrQMz5d59f2O","artist_name":"Mayer Hawthorne","album_id":"4FF4II3GGoTuYRW3zenamA","feats":"","feats_ids":"","name":"Where Does This Door Go","duration_ms":258026,"track_number":12,"track_type":"track"},{"id":"2ctu6RZhti1UHpysFprVJH","explicit":false,"artist_id":"4d53BMrRlQkrQMz5d59f2O","artist_name":"Mayer Hawthorne","album_id":"4FF4II3GGoTuYRW3zenamA","feats":"","feats_ids":"","name":"Robot Love","duration_ms":207293,"track_number":13,"track_type":"track"},{"id":"3vNmdY9II8697Cde7qYFjW","explicit":false,"artist_id":"4d53BMrRlQkrQMz5d59f2O","artist_name":"Mayer Hawthorne","album_id":"4FF4II3GGoTuYRW3zenamA","feats":"","feats_ids":"","name":"The Stars Are Ours","duration_ms":267520,"track_number":14,"track_type":"track"},{"id":"1BgtDv0gzK3vSDz0Si3mde","explicit":false,"artist_id":"4d53BMrRlQkrQMz5d59f2O","artist_name":"Mayer Hawthorne","album_id":"4FF4II3GGoTuYRW3zenamA","feats":"","feats_ids":"","name":"All Better","duration_ms":260360,"track_number":15,"track_type":"track"},{"id":"7edIiJ9gzZO3NSHpTqYGfG","explicit":false,"artist_id":"4d53BMrRlQkrQMz5d59f2O","artist_name":"Mayer Hawthorne","album_id":"4FF4II3GGoTuYRW3zenamA","feats":"","feats_ids":"","name":"Fool - Bonus Track","duration_ms":188133,"track_number":1,"track_type":"track"},{"id":"6BqoBqJblE9dOQFa3RZljt","explicit":false,"artist_id":"4d53BMrRlQkrQMz5d59f2O","artist_name":"Mayer Hawthorne","album_id":"4FF4II3GGoTuYRW3zenamA","feats":"","feats_ids":"","name":"Kaila - Bonus Track","duration_ms":237920,"track_number":2,"track_type":"track"},{"id":"1tRS6fqtkIldgnLmjKQ0sT","explicit":false,"artist_id":"4d53BMrRlQkrQMz5d59f2O","artist_name":"Mayer Hawthorne","album_id":"4FF4II3GGoTuYRW3zenamA","feats":"","feats_ids":"","name":"Small Clone - Bonus Track","duration_ms":237840,"track_number":3,"track_type":"track"},{"id":"7v9sByC4bJuaMG7f3IpKmT","explicit":false,"artist_id":"4d53BMrRlQkrQMz5d59f2O","artist_name":"Mayer Hawthorne","album_id":"4FF4II3GGoTuYRW3zenamA","feats":"","feats_ids":"","name":"Designer Drug - Bonus Track","duration_ms":213253,"track_number":4,"track_type":"track"}]