[{"id":"3ZVw1HR1QAQoKBygbhG4CE","explicit":false,"artist_id":"55Aa2cqylxrFIXC767Z865","artist_name":"Lil Wayne","album_id":"50yFYgKdwJANZ5O9MIbMkg","feats":"","feats_ids":"","name":"I Love You Dwayne","duration_ms":120302,"track_number":1,"track_type":"track"},{"id":"5BQrp63SHCVf4bzCzJePne","explicit":true,"artist_id":"55Aa2cqylxrFIXC767Z865","artist_name":"Lil Wayne","album_id":"50yFYgKdwJANZ5O9MIbMkg","feats":"XXXTENTACION","feats_ids":"15UsOTVnJzReFVN1VCnxy4","name":"Don't Cry (feat. XXXTENTACION)","duration_ms":249450,"track_number":2,"track_type":"track"},{"id":"0Y7di9ZCmB6Elad5WISaPc","explicit":true,"artist_id":"55Aa2cqylxrFIXC767Z865","artist_name":"Lil Wayne","album_id":"50yFYgKdwJANZ5O9MIbMkg","feats":"","feats_ids":"","name":"Dedicate","duration_ms":189908,"track_number":3,"track_type":"track"},{"id":"3wScL5W8H40zzCKN0atfBk","explicit":true,"artist_id":"55Aa2cqylxrFIXC767Z865","artist_name":"Lil Wayne","album_id":"50yFYgKdwJANZ5O9MIbMkg","feats":"Swizz Beatz","feats_ids":"2cADQgiLMjNhbsfeN52Bf3","name":"Uproar","duration_ms":194184,"track_number":4,"track_type":"track"},{"id":"0CBQ0m3mufWH75LTYB3s6h","explicit":true,"artist_id":"55Aa2cqylxrFIXC767Z865","artist_name":"Lil Wayne","album_id":"50yFYgKdwJANZ5O9MIbMkg","feats":"Travis Scott","feats_ids":"0Y5tJX1MQlPlqiwlOH1tJY","name":"Let It Fly (feat. Travis Scott)","duration_ms":186872,"track_number":5,"track_type":"track"},{"id":"5cGpjfgAvidLy6znwkCxkP","explicit":true,"artist_id":"55Aa2cqylxrFIXC767Z865","artist_name":"Lil Wayne","album_id":"50yFYgKdwJANZ5O9MIbMkg","feats":"","feats_ids":"","name":"Can't Be Broken","duration_ms":193243,"track_number":6,"track_type":"track"},{"id":"5IvdLxVB8gwwcgnEkXSSW2","explicit":false,"artist_id":"55Aa2cqylxrFIXC767Z865","artist_name":"Lil Wayne","album_id":"50yFYgKdwJANZ5O9MIbMkg","feats":"Nicki Minaj","feats_ids":"0hCNtLu0JehylgoiP8L4Gh","name":"Dark Side Of The Moon (feat. Nicki Minaj)","duration_ms":242972,"track_number":7,"track_type":"track"},{"id":"0dbTQYW3Ad1FTzIA9t90E8","explicit":true,"artist_id":"55Aa2cqylxrFIXC767Z865","artist_name":"Lil Wayne","album_id":"50yFYgKdwJANZ5O9MIbMkg","feats":"Kendrick Lamar","feats_ids":"2YZyLoL8N0Wb9xBt1NhZWg","name":"Mona Lisa (feat. Kendrick Lamar)","duration_ms":324189,"track_number":8,"track_type":"track"},{"id":"3JX0dOCIAiaR8MP3ryXWuM","explicit":true,"artist_id":"55Aa2cqylxrFIXC767Z865","artist_name":"Lil Wayne","album_id":"50yFYgKdwJANZ5O9MIbMkg","feats":"Sosamann","feats_ids":"3Bj81IbILbuj2uEwWXMdXI","name":"What About Me (feat. Sosamann)","duration_ms":216961,"track_number":9,"track_type":"track"},{"id":"2DnH4XlEkghUdE8ymdVom5","explicit":true,"artist_id":"55Aa2cqylxrFIXC767Z865","artist_name":"Lil Wayne","album_id":"50yFYgKdwJANZ5O9MIbMkg","feats":"","feats_ids":"","name":"Open Letter","duration_ms":269286,"track_number":10,"track_type":"track"},{"id":"05r1GGg1Rhs0RcUg27C82a","explicit":true,"artist_id":"55Aa2cqylxrFIXC767Z865","artist_name":"Lil Wayne","album_id":"50yFYgKdwJANZ5O9MIbMkg","feats":"Reginae Carter","feats_ids":"66jpZDjMcxF3SfDfwK7GXe","name":"Famous (feat. Reginae Carter)","duration_ms":242050,"track_number":11,"track_type":"track"},{"id":"0ubdf6zWT1It2saK41SkO0","explicit":true,"artist_id":"55Aa2cqylxrFIXC767Z865","artist_name":"Lil Wayne","album_id":"50yFYgKdwJANZ5O9MIbMkg","feats":"","feats_ids":"","name":"Problems","duration_ms":208504,"track_number":12,"track_type":"track"},{"id":"2AwyHlbA6f641SEkizD5JG","explicit":true,"artist_id":"55Aa2cqylxrFIXC767Z865","artist_name":"Lil Wayne","album_id":"50yFYgKdwJANZ5O9MIbMkg","feats":"Snoop Dogg","feats_ids":"7hJcb9fa4alzcOq3EaNPoG","name":"Dope Niggaz (feat. Snoop Dogg)","duration_ms":205983,"track_number":13,"track_type":"track"},{"id":"5s6pKnF3ZPtuqvEx1i1V7U","explicit":true,"artist_id":"55Aa2cqylxrFIXC767Z865","artist_name":"Lil Wayne","album_id":"50yFYgKdwJANZ5O9MIbMkg","feats":"","feats_ids":"","name":"Hittas","duration_ms":223617,"track_number":14,"track_type":"track"},{"id":"1Dk3CfJEtqvj7Xg2AWwfEn","explicit":true,"artist_id":"55Aa2cqylxrFIXC767Z865","artist_name":"Lil Wayne","album_id":"50yFYgKdwJANZ5O9MIbMkg","feats":"","feats_ids":"","name":"Took His Time","duration_ms":262399,"track_number":15,"track_type":"track"},{"id":"7EgI0dCaQuHFe3OTj5EpWI","explicit":true,"artist_id":"55Aa2cqylxrFIXC767Z865","artist_name":"Lil Wayne","album_id":"50yFYgKdwJANZ5O9MIbMkg","feats":"","feats_ids":"","name":"Open Safe","duration_ms":223938,"track_number":16,"track_type":"track"},{"id":"6wqWfSOZvTK18SAczoYm1L","explicit":true,"artist_id":"55Aa2cqylxrFIXC767Z865","artist_name":"Lil Wayne","album_id":"50yFYgKdwJANZ5O9MIbMkg","feats":"Ashanti, Mack Maine","feats_ids":"5rkVyNGXEgeUqKkB5ccK83, 18AOdS1Qw4XXnQSiPJQr1B","name":"Start This Shit Off Right (feat. Ashanti & Mack Maine)","duration_ms":280309,"track_number":17,"track_type":"track"},{"id":"1kaxyXcAi5ZHF3Q94QXsHK","explicit":true,"artist_id":"55Aa2cqylxrFIXC767Z865","artist_name":"Lil Wayne","album_id":"50yFYgKdwJANZ5O9MIbMkg","feats":"","feats_ids":"","name":"Demon","duration_ms":214313,"track_number":18,"track_type":"track"},{"id":"6y4pOReFqH2wzo4CV91cZC","explicit":true,"artist_id":"55Aa2cqylxrFIXC767Z865","artist_name":"Lil Wayne","album_id":"50yFYgKdwJANZ5O9MIbMkg","feats":"","feats_ids":"","name":"Mess","duration_ms":212427,"track_number":19,"track_type":"track"},{"id":"7cG6SxmQ24hQWnR8UThrk2","explicit":true,"artist_id":"55Aa2cqylxrFIXC767Z865","artist_name":"Lil Wayne","album_id":"50yFYgKdwJANZ5O9MIbMkg","feats":"Nivea","feats_ids":"15Dh5PvHQj909E0RgAe0aN","name":"Dope New Gospel (feat. Nivea)","duration_ms":207186,"track_number":20,"track_type":"track"},{"id":"4E3qImtJzRqLt8ZZyLceOE","explicit":true,"artist_id":"55Aa2cqylxrFIXC767Z865","artist_name":"Lil Wayne","album_id":"50yFYgKdwJANZ5O9MIbMkg","feats":"","feats_ids":"","name":"Perfect Strangers","duration_ms":249751,"track_number":21,"track_type":"track"},{"id":"68lOQPb5tX8U2cQRuas0L2","explicit":true,"artist_id":"55Aa2cqylxrFIXC767Z865","artist_name":"Lil Wayne","album_id":"50yFYgKdwJANZ5O9MIbMkg","feats":"","feats_ids":"","name":"Used 2","duration_ms":240199,"track_number":22,"track_type":"track"},{"id":"3BUWNzPWz2mDbptZmGEXpB","explicit":true,"artist_id":"55Aa2cqylxrFIXC767Z865","artist_name":"Lil Wayne","album_id":"50yFYgKdwJANZ5O9MIbMkg","feats":"","feats_ids":"","name":"Let It All Work Out","duration_ms":316192,"track_number":23,"track_type":"track"}]