[{"id":"2iZCGgWrIYu5tEM7dssZXB","explicit":false,"artist_id":"68NOjWuVYBRXzYwhel3jAl","artist_name":"SIAMES","album_id":"54Tu4voMoq7IC5lEAFiOsn","feats":"","feats_ids":"","name":"Home","duration_ms":39135,"track_number":1,"track_type":"track"},{"id":"7MwyCLXQ2OH3NAfz7ct0rE","explicit":false,"artist_id":"68NOjWuVYBRXzYwhel3jAl","artist_name":"SIAMES","album_id":"54Tu4voMoq7IC5lEAFiOsn","feats":"","feats_ids":"","name":"No Lullaby","duration_ms":201739,"track_number":2,"track_type":"track"},{"id":"4bjILXJfBlJ0zNNqnJpawP","explicit":false,"artist_id":"68NOjWuVYBRXzYwhel3jAl","artist_name":"SIAMES","album_id":"54Tu4voMoq7IC5lEAFiOsn","feats":"","feats_ids":"","name":"I Can't Wait","duration_ms":173124,"track_number":3,"track_type":"track"},{"id":"6zRBNkFmcNLgb3mOLmUK8i","explicit":false,"artist_id":"68NOjWuVYBRXzYwhel3jAl","artist_name":"SIAMES","album_id":"54Tu4voMoq7IC5lEAFiOsn","feats":"Barbie Williams","feats_ids":"56v6nmscLs2EGMSvg3JrQI","name":"Summer Nights","duration_ms":215500,"track_number":4,"track_type":"track"},{"id":"2Hla6QVdb2fJhQonnGLksC","explicit":false,"artist_id":"68NOjWuVYBRXzYwhel3jAl","artist_name":"SIAMES","album_id":"54Tu4voMoq7IC5lEAFiOsn","feats":"Eddy Capparelli","feats_ids":"0mTZ2QfipeprUoEIAQ27VW","name":"Brothers","duration_ms":245500,"track_number":5,"track_type":"track"},{"id":"7iD5WRt5gLfLasNuFxIAzs","explicit":false,"artist_id":"68NOjWuVYBRXzYwhel3jAl","artist_name":"SIAMES","album_id":"54Tu4voMoq7IC5lEAFiOsn","feats":"Barbie Williams","feats_ids":"56v6nmscLs2EGMSvg3JrQI","name":"Easier","duration_ms":197375,"track_number":6,"track_type":"track"},{"id":"79WkM4qlSf5YMXwnceKK1d","explicit":false,"artist_id":"68NOjWuVYBRXzYwhel3jAl","artist_name":"SIAMES","album_id":"54Tu4voMoq7IC5lEAFiOsn","feats":"","feats_ids":"","name":"Young and Restless","duration_ms":229000,"track_number":7,"track_type":"track"},{"id":"7vFuxUEUrItwGfuIQFaAgD","explicit":false,"artist_id":"68NOjWuVYBRXzYwhel3jAl","artist_name":"SIAMES","album_id":"54Tu4voMoq7IC5lEAFiOsn","feats":"","feats_ids":"","name":"2 Feathers","duration_ms":184124,"track_number":8,"track_type":"track"},{"id":"3Gbj3APyVHwUzpnHBCtGKP","explicit":false,"artist_id":"68NOjWuVYBRXzYwhel3jAl","artist_name":"SIAMES","album_id":"54Tu4voMoq7IC5lEAFiOsn","feats":"","feats_ids":"","name":"The Protected","duration_ms":212940,"track_number":9,"track_type":"track"}]