[{"id":"1B5XhTdaW74cuN0v9UN3z4","explicit":true,"artist_id":"61bQ4nwIioR8w6PGxzpyY3","artist_name":"Rondodasosa","album_id":"55GlQ4Bu444ugMRB0Jz57P","feats":"Nko","feats_ids":"4kTOsBwxhA2Sn4PSs7PqnN","name":"NEW YORK","duration_ms":196190,"track_number":1,"track_type":"track"},{"id":"3u4cgzpoF8bLINkigw5qzf","explicit":false,"artist_id":"0QqmgpgI0C1DyyDk49vnxY","artist_name":"MV Killa","album_id":"55GlQ4Bu444ugMRB0Jz57P","feats":"","feats_ids":"","name":"PUORTEM RISPETT","duration_ms":205520,"track_number":2,"track_type":"track"},{"id":"7tQt9C4ZrqtQQk2SkPJzEr","explicit":false,"artist_id":"3av6zIgtT4g0kjJtDybSdb","artist_name":"Johnny Marsiglia","album_id":"55GlQ4Bu444ugMRB0Jz57P","feats":"","feats_ids":"","name":"Prime","duration_ms":130373,"track_number":3,"track_type":"track"},{"id":"4A59RQfsuXLysvvUkOe9rM","explicit":true,"artist_id":"1sybJwRGo9WiiqcZLzzAbS","artist_name":"Sacky","album_id":"55GlQ4Bu444ugMRB0Jz57P","feats":"Kilimoney","feats_ids":"01lVP0L85U9jYVREPOB8RG","name":"ASSISTE 2","duration_ms":158400,"track_number":4,"track_type":"track"},{"id":"0uE0ekLgmPUTWWhxDcTT8J","explicit":false,"artist_id":"0QqmgpgI0C1DyyDk49vnxY","artist_name":"MV Killa","album_id":"55GlQ4Bu444ugMRB0Jz57P","feats":"Geolier","feats_ids":"27LlKWxS3KXW7RRAxN5S8s","name":"ME VOGL BENE","duration_ms":186506,"track_number":5,"track_type":"track"},{"id":"33YclgrCdgh4hQpBYtDqWr","explicit":true,"artist_id":"6PsQc21YZU7WNfiODG69Qk","artist_name":"Tony Boy","album_id":"55GlQ4Bu444ugMRB0Jz57P","feats":"","feats_ids":"","name":"HOT","duration_ms":146776,"track_number":6,"track_type":"track"},{"id":"0vYu47IR8ZUeaPiUzgQflq","explicit":true,"artist_id":"3av6zIgtT4g0kjJtDybSdb","artist_name":"Johnny Marsiglia","album_id":"55GlQ4Bu444ugMRB0Jz57P","feats":"","feats_ids":"","name":"Dovrei","duration_ms":145840,"track_number":7,"track_type":"track"},{"id":"3wVUgnc9yMqkbbmvUrpMvP","explicit":true,"artist_id":"2ySYVtBVDE24iUcJGfHRka","artist_name":"Axell","album_id":"55GlQ4Bu444ugMRB0Jz57P","feats":"","feats_ids":"","name":"KILI KILI","duration_ms":179711,"track_number":8,"track_type":"track"},{"id":"5qI1K3m6h0x2lLZCXPXE0A","explicit":true,"artist_id":"3av6zIgtT4g0kjJtDybSdb","artist_name":"Johnny Marsiglia","album_id":"55GlQ4Bu444ugMRB0Jz57P","feats":"Mezzosangue","feats_ids":"63isdzBiMOaYkMiX6XddfB","name":"Anestetico","duration_ms":228706,"track_number":9,"track_type":"track"},{"id":"1ZUo06Su4SzgkeNddzgdGe","explicit":true,"artist_id":"0ErzCpIMyLcjPiwT4elrtZ","artist_name":"NLE Choppa","album_id":"55GlQ4Bu444ugMRB0Jz57P","feats":"","feats_ids":"","name":"SLUT ME OUT","duration_ms":123672,"track_number":10,"track_type":"track"},{"id":"2bm08X6sVGvL6eNNS5havG","explicit":true,"artist_id":"4O15NlyKLIASxsJ0PrXPfz","artist_name":"Lil Uzi Vert","album_id":"55GlQ4Bu444ugMRB0Jz57P","feats":"sped up nightcore, ARIZONATEARS","feats_ids":"0M2CO5ijP35MDhNwvpgxTV, 2xzyIzdjfeXX6FIQtlAAyw","name":"Watch This - ARIZONATEARS Pluggnb Remix","duration_ms":163139,"track_number":11,"track_type":"track"},{"id":"6SpWFl168M8N7lgTyrlzmO","explicit":false,"artist_id":"7c0XG5cIJTrrAgEC3ULPiq","artist_name":"Ty Dolla $ign","album_id":"55GlQ4Bu444ugMRB0Jz57P","feats":"","feats_ids":"","name":"Motion","duration_ms":148173,"track_number":12,"track_type":"track"},{"id":"5iHDsKHAN5yKSMVCqTZuVM","explicit":true,"artist_id":"2LIk90788K0zvyj2JJVwkJ","artist_name":"Jack Harlow","album_id":"55GlQ4Bu444ugMRB0Jz57P","feats":"","feats_ids":"","name":"They Don’t Love It","duration_ms":113292,"track_number":13,"track_type":"track"},{"id":"6RlLiOYGLfPTPE64kLIDFL","explicit":true,"artist_id":"31W5EY0aAly4Qieq6OFu6I","artist_name":"A Boogie Wit da Hoodie","album_id":"55GlQ4Bu444ugMRB0Jz57P","feats":"G-Eazy","feats_ids":"02kJSzxNuaWGqwubyUba0Z","name":"MVP","duration_ms":173948,"track_number":14,"track_type":"track"},{"id":"3cjHRBJfIKtlXFkdguxPOp","explicit":false,"artist_id":"4FcZfItjVIsfO9TynErl7X","artist_name":"Jubël","album_id":"55GlQ4Bu444ugMRB0Jz57P","feats":"NLE Choppa","feats_ids":"0ErzCpIMyLcjPiwT4elrtZ","name":"Triple A","duration_ms":158896,"track_number":15,"track_type":"track"},{"id":"2RqPwSumXt7OiBZfl04Qju","explicit":true,"artist_id":"4O15NlyKLIASxsJ0PrXPfz","artist_name":"Lil Uzi Vert","album_id":"55GlQ4Bu444ugMRB0Jz57P","feats":"","feats_ids":"","name":"Just Wanna Rock","duration_ms":123890,"track_number":16,"track_type":"track"},{"id":"72uIHzRp1HbZH4infkumuI","explicit":true,"artist_id":"61bQ4nwIioR8w6PGxzpyY3","artist_name":"Rondodasosa","album_id":"55GlQ4Bu444ugMRB0Jz57P","feats":"Nko, NLE Choppa","feats_ids":"4kTOsBwxhA2Sn4PSs7PqnN, 0ErzCpIMyLcjPiwT4elrtZ","name":"WE ON EM","duration_ms":192558,"track_number":17,"track_type":"track"},{"id":"2Te8yTyL5KZGUbUtzzjZpe","explicit":true,"artist_id":"13y7CgLHjMVRMDqxdx0Xdo","artist_name":"Gucci Mane","album_id":"55GlQ4Bu444ugMRB0Jz57P","feats":"Roddy Ricch, Nardo Wick","feats_ids":"757aE44tKEUQEqRuT6GnEB, 0Njy6yR9LykNKYg9yE23QN","name":"Pissy","duration_ms":218172,"track_number":18,"track_type":"track"},{"id":"48rS0CMZSQ0scu1LyTMpkk","explicit":true,"artist_id":"0ErzCpIMyLcjPiwT4elrtZ","artist_name":"NLE Choppa","album_id":"55GlQ4Bu444ugMRB0Jz57P","feats":"Lil Wayne","feats_ids":"55Aa2cqylxrFIXC767Z865","name":"AIN'T GONNA ANSWER","duration_ms":187453,"track_number":19,"track_type":"track"},{"id":"16ETdIV22X0s2RGGVUDNd0","explicit":true,"artist_id":"31W5EY0aAly4Qieq6OFu6I","artist_name":"A Boogie Wit da Hoodie","album_id":"55GlQ4Bu444ugMRB0Jz57P","feats":"Kodak Black","feats_ids":"46SHBwWsqBkxI7EeeBEQG7","name":"Water (Drowning Pt. 2)","duration_ms":206769,"track_number":20,"track_type":"track"},{"id":"0jKVTCPC5vEVWxsxVhyCVa","explicit":true,"artist_id":"13y7CgLHjMVRMDqxdx0Xdo","artist_name":"Gucci Mane","album_id":"55GlQ4Bu444ugMRB0Jz57P","feats":"Drake","feats_ids":"3TVXtAsR1Inumwj472S9r4","name":"Both","duration_ms":190311,"track_number":21,"track_type":"track"},{"id":"71qblGD2mAA8LFVbQ6d4Ko","explicit":true,"artist_id":"0ErzCpIMyLcjPiwT4elrtZ","artist_name":"NLE Choppa","album_id":"55GlQ4Bu444ugMRB0Jz57P","feats":"","feats_ids":"","name":"TALK DIFFERENT","duration_ms":220556,"track_number":22,"track_type":"track"},{"id":"6BcHccQUORgvTSm4ymNUlp","explicit":true,"artist_id":"1YRqgFNXqRyMDRr8ClS1NL","artist_name":"Kaliii","album_id":"55GlQ4Bu444ugMRB0Jz57P","feats":"","feats_ids":"","name":"Area Codes","duration_ms":139325,"track_number":23,"track_type":"track"},{"id":"28KqQ9puOR0ewKm9BENH44","explicit":true,"artist_id":"2LIk90788K0zvyj2JJVwkJ","artist_name":"Jack Harlow","album_id":"55GlQ4Bu444ugMRB0Jz57P","feats":"","feats_ids":"","name":"First Class","duration_ms":173947,"track_number":24,"track_type":"track"},{"id":"7h5NXzMHHSCh90VBSg2ewn","explicit":true,"artist_id":"137W8MRPWKqSmrBGDBFSop","artist_name":"Wiz Khalifa","album_id":"55GlQ4Bu444ugMRB0Jz57P","feats":"","feats_ids":"","name":"Still Wiz","duration_ms":170987,"track_number":25,"track_type":"track"},{"id":"00IA8CW9k62gNvhHPRJUNX","explicit":true,"artist_id":"4kYSro6naA4h99UJvo89HB","artist_name":"Cardi B","album_id":"55GlQ4Bu444ugMRB0Jz57P","feats":"Kanye West, Lil Durk","feats_ids":"5K4W6rqBFWDnAN6FQUkS6x, 3hcs9uc56yIGFCSy9leWe7","name":"Hot Shit","duration_ms":211649,"track_number":26,"track_type":"track"},{"id":"56UBN9rzaUAavamMd6eL2X","explicit":true,"artist_id":"46SHBwWsqBkxI7EeeBEQG7","artist_name":"Kodak Black","album_id":"55GlQ4Bu444ugMRB0Jz57P","feats":"","feats_ids":"","name":"Super Gremlin","duration_ms":200547,"track_number":27,"track_type":"track"},{"id":"7DY0XnDOUJS6VFMp7Q4CEk","explicit":true,"artist_id":"2hlmm7s2ICUX0LVIhVFlZQ","artist_name":"Gunna","album_id":"55GlQ4Bu444ugMRB0Jz57P","feats":"Future, Young Thug","feats_ids":"1RyvyyTE3xzB2ZywiAwp0i, 50co4Is1HCEo8bhOyUWKpn","name":"Pushin P","duration_ms":136266,"track_number":28,"track_type":"track"},{"id":"7nzG1cSLMEwLEtb52lzqHW","explicit":true,"artist_id":"4Gso3d4CscCijv0lmajZWs","artist_name":"Don Toliver","album_id":"55GlQ4Bu444ugMRB0Jz57P","feats":"","feats_ids":"","name":"After Party","duration_ms":167915,"track_number":29,"track_type":"track"},{"id":"6REiPebDLqApYFZ9siKFOb","explicit":true,"artist_id":"2LIk90788K0zvyj2JJVwkJ","artist_name":"Jack Harlow","album_id":"55GlQ4Bu444ugMRB0Jz57P","feats":"","feats_ids":"","name":"Tyler Herro","duration_ms":156578,"track_number":30,"track_type":"track"},{"id":"3imjha563a2dG1NyDPT4mr","explicit":true,"artist_id":"0huGjMyP507tBCARyzSkrv","artist_name":"Cordae","album_id":"55GlQ4Bu444ugMRB0Jz57P","feats":"Gunna","feats_ids":"2hlmm7s2ICUX0LVIhVFlZQ","name":"Today","duration_ms":182068,"track_number":31,"track_type":"track"},{"id":"2gpafFJm8utiU5tlcUAgUH","explicit":true,"artist_id":"31W5EY0aAly4Qieq6OFu6I","artist_name":"A Boogie Wit da Hoodie","album_id":"55GlQ4Bu444ugMRB0Jz57P","feats":"Young Thug","feats_ids":"50co4Is1HCEo8bhOyUWKpn","name":"Might Not Give Up","duration_ms":225265,"track_number":32,"track_type":"track"},{"id":"1z4Q9nQrcBDXgTSF04kxJ7","explicit":true,"artist_id":"7c0XG5cIJTrrAgEC3ULPiq","artist_name":"Ty Dolla $ign","album_id":"55GlQ4Bu444ugMRB0Jz57P","feats":"Post Malone","feats_ids":"246dkjvS1zLTtiykXe5h60","name":"Spicy","duration_ms":143375,"track_number":33,"track_type":"track"},{"id":"0WYXBT6fafmVYmkSCBypA4","explicit":true,"artist_id":"0du5cEVh5yTK9QJze8zA0C","artist_name":"Bruno Mars","album_id":"55GlQ4Bu444ugMRB0Jz57P","feats":"Gucci Mane, Kodak Black","feats_ids":"13y7CgLHjMVRMDqxdx0Xdo, 46SHBwWsqBkxI7EeeBEQG7","name":"Wake Up in the Sky","duration_ms":203161,"track_number":34,"track_type":"track"}]